str_util/__init__.py
test/__init__.py
test/test.py
str_util-0.1.3.dist-info/LICENSE
str_util-0.1.3.dist-info/METADATA
str_util-0.1.3.dist-info/WHEEL
str_util-0.1.3.dist-info/top_level.txt
str_util-0.1.3.dist-info/RECORD
