Metadata-Version: 2.1
Name: str-util
Version: 0.1.3
Summary: String functions for Python 3
Home-page: https://github.com/majkilde/str_util.git
Author: Jakob Majkilde
Author-email: jakob@majkilde.dk
License: UNKNOWN
Platform: UNKNOWN
Classifier: Programming Language :: Python :: 3
Classifier: License :: OSI Approved :: MIT License
Classifier: Operating System :: OS Independent
